README.txt
setup.cfg
setup.py
docs/HISTORY.txt
docs/LICENSE.GPL
docs/LICENSE.txt
raptus/__init__.py
raptus.torii.plone.egg-info/PKG-INFO
raptus.torii.plone.egg-info/SOURCES.txt
raptus.torii.plone.egg-info/dependency_links.txt
raptus.torii.plone.egg-info/entry_points.txt
raptus.torii.plone.egg-info/namespace_packages.txt
raptus.torii.plone.egg-info/not-zip-safe
raptus.torii.plone.egg-info/requires.txt
raptus.torii.plone.egg-info/top_level.txt
raptus/torii/__init__.py
raptus/torii/plone/__init__.py
raptus/torii/plone/scripts/quickinstall.py
raptus/torii/plone/scripts/rebuild_catalogs.py